CHANGES.rst
CONTRIBUTORS.rst
DEVELOP.rst
LICENSE.GPL
LICENSE.rst
MANIFEST.in
README.rst
constraints.txt
constraints_plone52.txt
requirements.txt
setup.cfg
setup.py
docs/index.rst
src/redturtle/__init__.py
src/redturtle.importer.base.egg-info/PKG-INFO
src/redturtle.importer.base.egg-info/SOURCES.txt
src/redturtle.importer.base.egg-info/dependency_links.txt
src/redturtle.importer.base.egg-info/entry_points.txt
src/redturtle.importer.base.egg-info/namespace_packages.txt
src/redturtle.importer.base.egg-info/not-zip-safe
src/redturtle.importer.base.egg-info/requires.txt
src/redturtle.importer.base.egg-info/top_level.txt
src/redturtle/importer/__init__.py
src/redturtle/importer/base/__init__.py
src/redturtle/importer/base/configure.zcml
src/redturtle/importer/base/interfaces.py
src/redturtle/importer/base/testing.py
src/redturtle/importer/base/browser/__init__.py
src/redturtle/importer/base/browser/broken_links.py
src/redturtle/importer/base/browser/configure.zcml
src/redturtle/importer/base/browser/migrations.py
src/redturtle/importer/base/browser/templates/broken_links.pt
src/redturtle/importer/base/browser/templates/migration.pt
src/redturtle/importer/base/browser/templates/migration_result.pt
src/redturtle/importer/base/tests/__init__.py
src/redturtle/importer/base/tests/test_migration.py
src/redturtle/importer/base/tests/test_types_mapping.py
src/redturtle/importer/base/tests/custom_configs/custom_path.cfg
src/redturtle/importer/base/tests/custom_configs/import_users_and_groups.cfg
src/redturtle/importer/base/tests/custom_configs/skip_private.cfg
src/redturtle/importer/base/tests/robot/test_example.robot
src/redturtle/importer/base/transmogrifier/__init__.py
src/redturtle/importer/base/transmogrifier/configure.zcml
src/redturtle/importer/base/transmogrifier/migration_config.cfg
src/redturtle/importer/base/transmogrifier/transmogrifier.py
src/redturtle/importer/base/transmogrifier/types_mapping.py
src/redturtle/importer/base/transmogrifier/utils.py
src/redturtle/importer/base/transmogrifier/blueprints/__init__.py
src/redturtle/importer/base/transmogrifier/blueprints/browserdefault.py
src/redturtle/importer/base/transmogrifier/blueprints/cioppino.py
src/redturtle/importer/base/transmogrifier/blueprints/commit.py
src/redturtle/importer/base/transmogrifier/blueprints/configure.zcml
src/redturtle/importer/base/transmogrifier/blueprints/constructor.py
